TALDCommands/TALDCommands.py
TALDCommands/__init__.py
TALDCommands-2.0.0.dist-info/METADATA
TALDCommands-2.0.0.dist-info/WHEEL
TALDCommands-2.0.0.dist-info/top_level.txt
TALDCommands-2.0.0.dist-info/RECORD
