Metadata-Version: 2.1
Name: TALDCommands
Version: 2.0.0
Summary: Suspicious commands
Author: Mohamed Rayan Ettaldi
Author-email: <taldtool06@gmail.com>
Keywords: python
Classifier: Development Status :: 1 - Planning
Classifier: Intended Audience :: Developers
Classifier: Programming Language :: Python :: 3
Classifier: Operating System :: Unix
Classifier: Operating System :: MacOS :: MacOS X
Classifier: Operating System :: Microsoft :: Windows
